aws_sso_util/__init__.py
aws_sso_util/__main__.py
aws_sso_util/assignments.py
aws_sso_util/cfn.py
aws_sso_util/cfn_lib/__init__.py
aws_sso_util/cfn_lib/cfn_yaml_tags.py
aws_sso_util/cfn_lib/config.py
aws_sso_util/cfn_lib/macro.py
aws_sso_util/cfn_lib/resources.py
aws_sso_util/cfn_lib/templates.py
aws_sso_util/cfn_lib/utils.py
aws_sso_util/check.py
aws_sso_util/cli.py
aws_sso_util/configure_profile.py
aws_sso_util/console.py
aws_sso_util/credential_process.py
aws_sso_util/deploy_macro.py
aws_sso_util/login.py
aws_sso_util/logout.py
aws_sso_util/lookup.py
aws_sso_util/populate_profiles.py
aws_sso_util/roles.py
aws_sso_util/run_as.py
aws_sso_util/utils.py
aws_sso_util-4.33.0.dist-info/METADATA
aws_sso_util-4.33.0.dist-info/WHEEL
aws_sso_util-4.33.0.dist-info/entry_points.txt
aws_sso_util-4.33.0.dist-info/RECORD
