Metadata-Version: 2.1
Name: aws-sso-util
Version: 4.33.0
Summary: Utilities to make AWS SSO easier
Home-page: https://github.com/benkehoe/aws-sso-util
License: Apache-2.0
Author: Ben Kehoe
Author-email: ben@kehoe.io
Requires-Python: >=3.7,<4.0
Classifier: Development Status :: 4 - Beta
Classifier: Intended Audience :: Developers
Classifier: Intended Audience :: System Administrators
Classifier: License :: OSI Approved :: Apache Software License
Classifier: Operating System :: OS Independent
Classifier: Programming Language :: Python :: 3
Classifier: Programming Language :: Python :: 3.7
Classifier: Programming Language :: Python :: 3.8
Classifier: Programming Language :: Python :: 3.9
Classifier: Programming Language :: Python :: 3.10
Classifier: Programming Language :: Python :: 3.11
Classifier: Programming Language :: Python :: 3.12
Classifier: Topic :: Utilities
Requires-Dist: aws-error-utils (>=2.4,<3.0)
Requires-Dist: aws-sso-lib (>=1.13.0,<2.0.0)
Requires-Dist: boto3 (>=1.24.60,<2.0.0)
Requires-Dist: click (>=8.0.0,<9.0.0)
Requires-Dist: jsonschema (>=4.0.1,<5.0.0)
Requires-Dist: python-dateutil (>=2.8.1,<3.0.0)
Requires-Dist: pyyaml (>=6.0.1,<7.0.0)
Requires-Dist: requests (>=2.26.0,<3.0.0)
Project-URL: Repository, https://github.com/benkehoe/aws-sso-util
